kerrgeodesic_gw/__init__.py
kerrgeodesic_gw/astro_data.py
kerrgeodesic_gw/gw_blob.py
kerrgeodesic_gw/gw_particle.py
kerrgeodesic_gw/kerr_geodesic.py
kerrgeodesic_gw/kerr_spacetime.py
kerrgeodesic_gw/lisa_detector.py
kerrgeodesic_gw/signal_processing.py
kerrgeodesic_gw/spin_weighted_spherical_harm.py
kerrgeodesic_gw/spin_weighted_spheroidal_harm.py
kerrgeodesic_gw/utilities.py
kerrgeodesic_gw/zinf.py
kerrgeodesic_gw/data/Sensitivity_LISA_SciRD1806_Alloc.dat
kerrgeodesic_gw/data/Zinf_a0.0.dat
kerrgeodesic_gw/data/Zinf_a0.1.dat
kerrgeodesic_gw/data/Zinf_a0.2.dat
kerrgeodesic_gw/data/Zinf_a0.3.dat
kerrgeodesic_gw/data/Zinf_a0.4.dat
kerrgeodesic_gw/data/Zinf_a0.5.dat
kerrgeodesic_gw/data/Zinf_a0.6.dat
kerrgeodesic_gw/data/Zinf_a0.7.dat
kerrgeodesic_gw/data/Zinf_a0.8.dat
kerrgeodesic_gw/data/Zinf_a0.9.dat
kerrgeodesic_gw/data/Zinf_a0.95.dat
kerrgeodesic_gw/data/Zinf_a0.98.dat
kerrgeodesic_gw-0.5.dist-info/LICENSE
kerrgeodesic_gw-0.5.dist-info/METADATA
kerrgeodesic_gw-0.5.dist-info/WHEEL
kerrgeodesic_gw-0.5.dist-info/top_level.txt
kerrgeodesic_gw-0.5.dist-info/RECORD
