Metadata-Version: 2.1
Name: kerrgeodesic-gw
Version: 0.5
Summary: Gravitational radiation from material orbiting a Kerr black hole
Home-page: https://github.com/BlackHolePerturbationToolkit/kerrgeodesic_gw
Author: Eric Gourgoulhon, Alexandre Le Tiec, Frederic Vincent, Niels Warburton
Author-email: eric.gourgoulhon@obspm.fr
License: GPLv2+
Keywords: SageMath
Classifier: Development Status :: 4 - Beta
Classifier: Intended Audience :: Science/Research
Classifier: Topic :: Scientific/Engineering :: Mathematics
Classifier: Topic :: Scientific/Engineering :: Physics
Classifier: Topic :: Scientific/Engineering :: Astronomy
Classifier: License :: OSI Approved :: GNU General Public License v2 or later (GPLv2+)
Classifier: Programming Language :: Python :: 3
License-File: LICENSE
Requires-Dist: sphinx
Provides-Extra: passagemath
Requires-Dist: passagemath-symbolics[plot,test] ; extra == 'passagemath'
